README
setup.py
pyyaks/__init__.py
pyyaks/context.py
pyyaks/fileutil.py
pyyaks/logger.py
pyyaks/pexpect.py
pyyaks/shell.py
pyyaks/task.py
pyyaks.egg-info/PKG-INFO
pyyaks.egg-info/SOURCES.txt
pyyaks.egg-info/dependency_links.txt
pyyaks.egg-info/top_level.txt
pyyaks/tests/__init__.py
pyyaks/tests/test_context.py
pyyaks/tests/test_logger.py
pyyaks/tests/test_render.py