Metadata-Version: 1.0
Name: pyyaks
Version: 3.3.3
Summary: Pipeline processing toolkit
Home-page: http://cxc.harvard.edu/contrib/pyyaks
Author: Tom Aldcroft
Author-email: aldcroft@head.cfa.harvard.edu
License: UNKNOWN
Platform: UNKNOWN
